webdataset/__init__.py
webdataset/__init__.pyi
webdataset/autodecode.py
webdataset/autodecode.pyi
webdataset/cache.py
webdataset/cache.pyi
webdataset/compat.py
webdataset/compat.pyi
webdataset/downloader.pyi
webdataset/extradatasets.py
webdataset/extradatasets.pyi
webdataset/filters.py
webdataset/filters.pyi
webdataset/gopen.py
webdataset/gopen.pyi
webdataset/handlers.py
webdataset/handlers.pyi
webdataset/mix.py
webdataset/mix.pyi
webdataset/multi.py
webdataset/multi.pyi
webdataset/pipeline.py
webdataset/pipeline.pyi
webdataset/pytorch.py
webdataset/pytorch.pyi
webdataset/shardlists.py
webdataset/shardlists.pyi
webdataset/tariterators.py
webdataset/tariterators.pyi
webdataset/tenbin.py
webdataset/tenbin.pyi
webdataset/typecheck.py
webdataset/typecheck.pyi
webdataset/utils.py
webdataset/utils.pyi
webdataset/writer.py
webdataset/writer.pyi
webdatasetng-1.0.1.dist-info/licenses/LICENSE
webdatasetng-1.0.1.dist-info/METADATA
webdatasetng-1.0.1.dist-info/WHEEL
webdatasetng-1.0.1.dist-info/top_level.txt
webdatasetng-1.0.1.dist-info/RECORD
